jupyter_notebook_parser/__init__.py
jupyter_notebook_parser/container.py
jupyter_notebook_parser/parser.py
jupyter_notebook_parser/rewriter.py
jupyter_notebook_parser-0.1.4.dist-info/LICENSE
jupyter_notebook_parser-0.1.4.dist-info/METADATA
jupyter_notebook_parser-0.1.4.dist-info/WHEEL
jupyter_notebook_parser-0.1.4.dist-info/top_level.txt
jupyter_notebook_parser-0.1.4.dist-info/RECORD
