Metadata-Version: 2.1
Name: jupyter-notebook-parser
Version: 0.1.4
Summary: A Python library that parses Jupyter notebook cells
Home-page: https://github.com/cyyc1/jupyter-notebook-parser
License: MIT
Classifier: License :: OSI Approved :: MIT License
Classifier: Programming Language :: Python :: 3
Classifier: Programming Language :: Python :: 3 :: Only
Requires-Python: >=3.7
License-File: LICENSE
